[{"place_id": 67721586, "licence": "Data \u00a9 OpenStreetMap contributors, ODbL 1.0. http://osm.org/copyright", "osm_type": "way", "osm_id": 62318614, "lat": "45.899592999999996", "lon": "11.043672950000001", "class": "building", "type": "yes", "place_rank": 30, "importance": 6.476157778281862e-05, "addresstype": "building", "name": "", "display_name": "10, Via Verdi, Brione, Rovereto, Comunit\u00e0 della Vallagarina, Provincia di Trento, Trentino \u2013 Alto Adige/S\u00fcdtirol, 38068, Italy", "boundingbox": ["45.8995192", "45.8996668", "11.0435601", "11.0437858"], "geojson": {"type": "Polygon", "coordinates": [[[11.0435601, 45.8996402], [11.0435949, 45.8995192], [11.0437858, 45.8995458], [11.043751, 45.8996668], [11.0435601, 45.8996402]]]}}]